cpimgs/__init__.py
cpimgs/cpimgs.py
cpimgs_yzhang250-0.0.6.dist-info/LICENSE
cpimgs_yzhang250-0.0.6.dist-info/METADATA
cpimgs_yzhang250-0.0.6.dist-info/WHEEL
cpimgs_yzhang250-0.0.6.dist-info/top_level.txt
cpimgs_yzhang250-0.0.6.dist-info/RECORD
