Metadata-Version: 2.1
Name: cpimgs-yzhang250
Version: 0.0.6
Summary: A package to get DMSO plates and wells coordinates, get CPD plates and wells coordinates, get images of the cells treated by the CPD and nearby DMSO.
Home-page: https://github.com/yzhang250
Author: Ye Zhang
Author-email: yzhang250@gmail.com
License: UNKNOWN
Platform: UNKNOWN
Classifier: Programming Language :: Python :: 3
Classifier: License :: OSI Approved :: MIT License
Classifier: Operating System :: OS Independent
Requires-Python: >=3.6
